django_editorjs2/__init__.py
django_editorjs2/apps.py
django_editorjs2/block_processor.py
django_editorjs2/blogapp/__init__.py
django_editorjs2/blogapp/admin.py
django_editorjs2/blogapp/apps.py
django_editorjs2/blogapp/migrations/0001_initial.py
django_editorjs2/blogapp/migrations/__init__.py
django_editorjs2/blogapp/models.py
django_editorjs2/blogapp/templates/django_editorjs2_blog/base.html
django_editorjs2/blogapp/templates/django_editorjs2_blog/post_detail.html
django_editorjs2/blogapp/templates/django_editorjs2_blog/post_form.html
django_editorjs2/blogapp/templates/django_editorjs2_blog/post_list.html
django_editorjs2/blogapp/tests.py
django_editorjs2/blogapp/urls.py
django_editorjs2/blogapp/utils.py
django_editorjs2/blogapp/views.py
django_editorjs2/fields.py
django_editorjs2/migrations/0001_initial.py
django_editorjs2/migrations/__init__.py
django_editorjs2/models.py
django_editorjs2/requirements.txt
django_editorjs2/screenshot.png
django_editorjs2/static/django_editorjs2/attaches.editorjs.min.js
django_editorjs2/static/django_editorjs2/buttonlink.js
django_editorjs2/static/django_editorjs2/checklist.editorjs.min.js
django_editorjs2/static/django_editorjs2/code.editorjs.min.js
django_editorjs2/static/django_editorjs2/delimiter.editorjs.min.js
django_editorjs2/static/django_editorjs2/editorjs.min.js
django_editorjs2/static/django_editorjs2/embed.editorjs.min.js
django_editorjs2/static/django_editorjs2/header.editorjs.min.js
django_editorjs2/static/django_editorjs2/image.editorjs.min.js
django_editorjs2/static/django_editorjs2/index.html
django_editorjs2/static/django_editorjs2/list.editorjs.min.js
django_editorjs2/static/django_editorjs2/marker.editorjs.min.js
django_editorjs2/static/django_editorjs2/quote.editorjs.min.js
django_editorjs2/static/django_editorjs2/table.editorjs.min.js
django_editorjs2/templates/django_editorjs2/widget/editorjs.html
django_editorjs2/urls.py
django_editorjs2/views.py
django_editorjs2-0.3.8.dist-info/LICENSE
django_editorjs2-0.3.8.dist-info/METADATA
django_editorjs2-0.3.8.dist-info/WHEEL
django_editorjs2-0.3.8.dist-info/RECORD
